meta_lbpt/__init__.py
meta_lbpt/ag.py
meta_lbpt/at.py
meta_lbpt/ch.py
meta_lbpt/rs.py
meta_lbpt/sc.py
meta_lbpt-1.1.0.dist-info/.ipynb_checkpoints/PKG-INFO-checkpoint
meta_lbpt-1.1.0.dist-info/.ipynb_checkpoints/SOURCES-checkpoint.txt
meta_lbpt-1.1.0.dist-info/.ipynb_checkpoints/dependency_links-checkpoint.txt
meta_lbpt-1.1.0.dist-info/.ipynb_checkpoints/top_level-checkpoint.txt
meta_lbpt-1.1.0.dist-info/METADATA
meta_lbpt-1.1.0.dist-info/WHEEL
meta_lbpt-1.1.0.dist-info/top_level.txt
meta_lbpt-1.1.0.dist-info/RECORD
