Metadata-Version: 2.4
Name: meta_lbpt
Version: 1.1.0
Summary: Algoritmos Metaheurísticos
Author: Luis Beltran Palma Ttito, Dennis Iván Candia Oviedo, Carlos Ramón Quispe Onofre, Willian Zamalloa Paro, José Mauro Pillco Quispe
Author-email: luis.palma@unsaac.edu.pe, dennis.candia@unsaac.edu.pe, carlos.quispe@unsaac.edu.pe, willian.zamalloa@unsaac.edu.pe, jose.pillco@unsaac.edu.pe
License: GPL
Dynamic: author
Dynamic: author-email
Dynamic: description
Dynamic: description-content-type
Dynamic: license
Dynamic: summary
